centernet_ilvo/__init__.py
centernet_ilvo/center.py
centernet_ilvo/centernet.py
centernet_ilvo/predict.py
centernet_ilvo/visuals.py
centernet_ilvo-0.0.1.post1.dist-info/LICENCE
centernet_ilvo-0.0.1.post1.dist-info/METADATA
centernet_ilvo-0.0.1.post1.dist-info/WHEEL
centernet_ilvo-0.0.1.post1.dist-info/top_level.txt
centernet_ilvo-0.0.1.post1.dist-info/RECORD
