Metadata-Version: 2.2
Name: centernet_ilvo
Version: 0.0.1.post1
Summary: The ilvo plant centre model package
Author-email: Axel Willekens <axel.willekens@ilvo.vlaanderen.be>
Classifier: Programming Language :: Python :: 3
Classifier: Operating System :: OS Independent
Requires-Python: >=3.9
License-File: LICENCE
Requires-Dist: numpy>=2.0.0
Requires-Dist: opencv-python>=4.8.0.74
Requires-Dist: scikit-image>=0.19.0
Requires-Dist: requests
Requires-Dist: toml
